{
  "method": "ilp",
  "nodes": [
    {
      "id": "n1",
      "type": "place",
      "label": "place_0"
    },
    {
      "id": "n2",
      "type": "place",
      "label": "place_1"
    },
    {
      "id": "n3",
      "type": "place",
      "label": "place_2"
    },
    {
      "id": "n4",
      "type": "place",
      "label": "place_3"
    },
    {
      "id": "n5",
      "type": "place",
      "label": "place_4"
    },
    {
      "id": "n6",
      "type": "place",
      "label": "place_5"
    },
    {
      "id": "n7",
      "type": "place",
      "label": "place_6"
    },
    {
      "id": "n8",
      "type": "place",
      "label": "place_7"
    },
    {
      "id": "n9",
      "type": "place",
      "label": "place_8"
    },
    {
      "id": "n10",
      "type": "place",
      "label": "place_9"
    },
    {
      "id": "n11",
      "type": "place",
      "label": "place_10"
    },
    {
      "id": "n12",
      "type": "place",
      "label": "place_11"
    },
    {
      "id": "n13",
      "type": "place",
      "label": "place_12"
    },
    {
      "id": "n14",
      "type": "place",
      "label": "place_13"
    },
    {
      "id": "n15",
      "type": "place",
      "label": "place_14"
    },
    {
      "id": "n16",
      "type": "place",
      "label": "place_15"
    },
    {
      "id": "n17",
      "type": "place",
      "label": "place_16"
    },
    {
      "id": "n18",
      "type": "place",
      "label": "place_17"
    },
    {
      "id": "n19",
      "type": "place",
      "label": "place_18"
    },
    {
      "id": "n20",
      "type": "place",
      "label": "place_19"
    },
    {
      "id": "n21",
      "type": "place",
      "label": "place_20"
    },
    {
      "id": "n22",
      "type": "place",
      "label": "place_21"
    },
    {
      "id": "n23",
      "type": "place",
      "label": "place_22"
    },
    {
      "id": "n24",
      "type": "place",
      "label": "place_23"
    },
    {
      "id": "n25",
      "type": "place",
      "label": "place_24"
    },
    {
      "id": "n26",
      "type": "place",
      "label": "place_25"
    },
    {
      "id": "n27",
      "type": "place",
      "label": "place_26"
    },
    {
      "id": "n28",
      "type": "place",
      "label": "place_27"
    },
    {
      "id": "n29",
      "type": "place",
      "label": "place_28"
    },
    {
      "id": "n30",
      "type": "place",
      "label": "place_29"
    },
    {
      "id": "n31",
      "type": "place",
      "label": "place_30"
    },
    {
      "id": "n32",
      "type": "place",
      "label": "place_31"
    },
    {
      "id": "n33",
      "type": "place",
      "label": "place_32"
    },
    {
      "id": "n34",
      "type": "place",
      "label": "place_33"
    },
    {
      "id": "n35",
      "type": "place",
      "label": "place_34"
    },
    {
      "id": "n36",
      "type": "place",
      "label": "place_35"
    },
    {
      "id": "n37",
      "type": "place",
      "label": "place_36"
    },
    {
      "id": "n38",
      "type": "place",
      "label": "place_37"
    },
    {
      "id": "n39",
      "type": "place",
      "label": "place_38"
    },
    {
      "id": "n40",
      "type": "place",
      "label": "place_39"
    },
    {
      "id": "n41",
      "type": "place",
      "label": "place_40"
    },
    {
      "id": "n42",
      "type": "place",
      "label": "place_41"
    },
    {
      "id": "n43",
      "type": "place",
      "label": "place_42"
    },
    {
      "id": "n44",
      "type": "place",
      "label": "place_43"
    },
    {
      "id": "n45",
      "type": "place",
      "label": "place_44"
    },
    {
      "id": "n46",
      "type": "place",
      "label": "place_45"
    },
    {
      "id": "n47",
      "type": "place",
      "label": "place_46"
    },
    {
      "id": "n48",
      "type": "place",
      "label": "place_47"
    },
    {
      "id": "n49",
      "type": "place",
      "label": "place_48"
    },
    {
      "id": "n50",
      "type": "place",
      "label": "place_49"
    },
    {
      "id": "n51",
      "type": "place",
      "label": "place_50"
    },
    {
      "id": "n52",
      "type": "place",
      "label": "place_51"
    },
    {
      "id": "n53",
      "type": "place",
      "label": "place_52"
    },
    {
      "id": "n54",
      "type": "place",
      "label": "place_53"
    },
    {
      "id": "n55",
      "type": "place",
      "label": "place_54"
    },
    {
      "id": "n56",
      "type": "place",
      "label": "place_55"
    },
    {
      "id": "n57",
      "type": "place",
      "label": "place_56"
    },
    {
      "id": "n58",
      "type": "place",
      "label": "place_57"
    },
    {
      "id": "n59",
      "type": "place",
      "label": "place_58"
    },
    {
      "id": "n60",
      "type": "place",
      "label": "place_59"
    },
    {
      "id": "n61",
      "type": "place",
      "label": "place_60"
    },
    {
      "id": "n62",
      "type": "place",
      "label": "place_61"
    },
    {
      "id": "n63",
      "type": "place",
      "label": "place_62"
    },
    {
      "id": "n64",
      "type": "place",
      "label": "place_63"
    },
    {
      "id": "n65",
      "type": "place",
      "label": "place_64"
    },
    {
      "id": "n66",
      "type": "place",
      "label": "place_65"
    },
    {
      "id": "n67",
      "type": "place",
      "label": "place_66"
    },
    {
      "id": "n68",
      "type": "place",
      "label": "place_67"
    },
    {
      "id": "n69",
      "type": "place",
      "label": "place_68"
    },
    {
      "id": "n70",
      "type": "place",
      "label": "place_69"
    },
    {
      "id": "n71",
      "type": "place",
      "label": "place_70"
    },
    {
      "id": "n72",
      "type": "place",
      "label": "place_71"
    },
    {
      "id": "n73",
      "type": "place",
      "label": "place_72"
    },
    {
      "id": "n74",
      "type": "place",
      "label": "place_73"
    },
    {
      "id": "n75",
      "type": "place",
      "label": "place_74"
    },
    {
      "id": "n76",
      "type": "place",
      "label": "place_75"
    },
    {
      "id": "n77",
      "type": "place",
      "label": "place_76"
    },
    {
      "id": "n78",
      "type": "place",
      "label": "place_77"
    },
    {
      "id": "n79",
      "type": "place",
      "label": "place_78"
    },
    {
      "id": "n80",
      "type": "place",
      "label": "place_79"
    },
    {
      "id": "n81",
      "type": "place",
      "label": "place_80"
    },
    {
      "id": "n82",
      "type": "place",
      "label": "place_81"
    },
    {
      "id": "n83",
      "type": "place",
      "label": "place_82"
    },
    {
      "id": "n84",
      "type": "place",
      "label": "place_83"
    },
    {
      "id": "n85",
      "type": "place",
      "label": "place_84"
    },
    {
      "id": "n86",
      "type": "place",
      "label": "place_85"
    },
    {
      "id": "n87",
      "type": "place",
      "label": "place_86"
    },
    {
      "id": "n88",
      "type": "place",
      "label": "place_87"
    },
    {
      "id": "n89",
      "type": "place",
      "label": "place_88"
    },
    {
      "id": "n90",
      "type": "place",
      "label": "place_89"
    },
    {
      "id": "n91",
      "type": "place",
      "label": "place_90"
    },
    {
      "id": "n92",
      "type": "place",
      "label": "place_91"
    },
    {
      "id": "n93",
      "type": "place",
      "label": "place_92"
    },
    {
      "id": "n94",
      "type": "place",
      "label": "place_93"
    },
    {
      "id": "n95",
      "type": "place",
      "label": "place_94"
    },
    {
      "id": "n96",
      "type": "place",
      "label": "place_95"
    },
    {
      "id": "n97",
      "type": "place",
      "label": "place_96"
    },
    {
      "id": "n98",
      "type": "place",
      "label": "place_97"
    },
    {
      "id": "n99",
      "type": "place",
      "label": "place_98"
    },
    {
      "id": "n100",
      "type": "place",
      "label": "place_99"
    },
    {
      "id": "n101",
      "type": "place",
      "label": "place_100"
    },
    {
      "id": "n102",
      "type": "place",
      "label": "place_101"
    },
    {
      "id": "n103",
      "type": "place",
      "label": "place_102"
    },
    {
      "id": "n104",
      "type": "place",
      "label": "place_103"
    },
    {
      "id": "n105",
      "type": "place",
      "label": "place_104"
    },
    {
      "id": "n106",
      "type": "place",
      "label": "sink"
    },
    {
      "id": "n107",
      "type": "place",
      "label": "source"
    },
    {
      "id": "n108",
      "type": "transition",
      "label": "IV Liquid"
    },
    {
      "id": "n109",
      "type": "transition",
      "label": "CRP"
    },
    {
      "id": "n110",
      "type": "transition",
      "label": "Admission NC"
    },
    {
      "id": "n111",
      "type": "transition",
      "label": "IV Antibiotics"
    },
    {
      "id": "n112",
      "type": "transition",
      "label": "Leucocytes"
    },
    {
      "id": "n113",
      "type": "transition",
      "label": "Release A"
    },
    {
      "id": "n114",
      "type": "transition",
      "label": "LacticAcid"
    },
    {
      "id": "n115",
      "type": "transition",
      "label": "ER Registration"
    },
    {
      "id": "n116",
      "type": "transition",
      "label": "[end]@1602163306789"
    },
    {
      "id": "n117",
      "type": "transition",
      "label": "ER Triage"
    },
    {
      "id": "n118",
      "type": "transition",
      "label": "[start>@1602163306789"
    },
    {
      "id": "n119",
      "type": "transition",
      "label": "Return ER"
    },
    {
      "id": "n120",
      "type": "transition",
      "label": "ER Sepsis Triage"
    }
  ],
  "edges": [
    {
      "source": "n40",
      "target": "n109"
    },
    {
      "source": "n115",
      "target": "n45"
    },
    {
      "source": "n99",
      "target": "n119"
    },
    {
      "source": "n67",
      "target": "n108"
    },
    {
      "source": "n118",
      "target": "n66"
    },
    {
      "source": "n119",
      "target": "n99"
    },
    {
      "source": "n115",
      "target": "n49"
    },
    {
      "source": "n112",
      "target": "n98"
    },
    {
      "source": "n50",
      "target": "n113"
    },
    {
      "source": "n108",
      "target": "n28"
    },
    {
      "source": "n87",
      "target": "n113"
    },
    {
      "source": "n51",
      "target": "n111"
    },
    {
      "source": "n112",
      "target": "n34"
    },
    {
      "source": "n118",
      "target": "n95"
    },
    {
      "source": "n119",
      "target": "n94"
    },
    {
      "source": "n113",
      "target": "n98"
    },
    {
      "source": "n111",
      "target": "n1"
    },
    {
      "source": "n96",
      "target": "n109"
    },
    {
      "source": "n19",
      "target": "n114"
    },
    {
      "source": "n110",
      "target": "n61"
    },
    {
      "source": "n113",
      "target": "n34"
    },
    {
      "source": "n110",
      "target": "n80"
    },
    {
      "source": "n117",
      "target": "n16"
    },
    {
      "source": "n55",
      "target": "n110"
    },
    {
      "source": "n114",
      "target": "n72"
    },
    {
      "source": "n81",
      "target": "n111"
    },
    {
      "source": "n98",
      "target": "n114"
    },
    {
      "source": "n43",
      "target": "n113"
    },
    {
      "source": "n94",
      "target": "n113"
    },
    {
      "source": "n76",
      "target": "n109"
    },
    {
      "source": "n110",
      "target": "n7"
    },
    {
      "source": "n116",
      "target": "n53"
    },
    {
      "source": "n46",
      "target": "n110"
    },
    {
      "source": "n102",
      "target": "n116"
    },
    {
      "source": "n99",
      "target": "n116"
    },
    {
      "source": "n10",
      "target": "n113"
    },
    {
      "source": "n83",
      "target": "n116"
    },
    {
      "source": "n101",
      "target": "n117"
    },
    {
      "source": "n95",
      "target": "n115"
    },
    {
      "source": "n108",
      "target": "n20"
    },
    {
      "source": "n111",
      "target": "n9"
    },
    {
      "source": "n23",
      "target": "n113"
    },
    {
      "source": "n28",
      "target": "n114"
    },
    {
      "source": "n97",
      "target": "n114"
    },
    {
      "source": "n73",
      "target": "n111"
    },
    {
      "source": "n120",
      "target": "n63"
    },
    {
      "source": "n54",
      "target": "n109"
    },
    {
      "source": "n117",
      "target": "n37"
    },
    {
      "source": "n115",
      "target": "n64"
    },
    {
      "source": "n120",
      "target": "n82"
    },
    {
      "source": "n77",
      "target": "n116"
    },
    {
      "source": "n114",
      "target": "n17"
    },
    {
      "source": "n49",
      "target": "n117"
    },
    {
      "source": "n109",
      "target": "n24"
    },
    {
      "source": "n55",
      "target": "n111"
    },
    {
      "source": "n2",
      "target": "n114"
    },
    {
      "source": "n105",
      "target": "n108"
    },
    {
      "source": "n120",
      "target": "n86"
    },
    {
      "source": "n87",
      "target": "n116"
    },
    {
      "source": "n91",
      "target": "n110"
    },
    {
      "source": "n118",
      "target": "n30"
    },
    {
      "source": "n110",
      "target": "n37"
    },
    {
      "source": "n53",
      "target": "n117"
    },
    {
      "source": "n108",
      "target": "n39"
    },
    {
      "source": "n4",
      "target": "n117"
    },
    {
      "source": "n40",
      "target": "n113"
    },
    {
      "source": "n111",
      "target": "n34"
    },
    {
      "source": "n80",
      "target": "n113"
    },
    {
      "source": "n108",
      "target": "n95"
    },
    {
      "source": "n40",
      "target": "n114"
    },
    {
      "source": "n108",
      "target": "n71"
    },
    {
      "source": "n120",
      "target": "n34"
    },
    {
      "source": "n108",
      "target": "n65"
    },
    {
      "source": "n113",
      "target": "n82"
    },
    {
      "source": "n114",
      "target": "n19"
    },
    {
      "source": "n61",
      "target": "n116"
    },
    {
      "source": "n109",
      "target": "n47"
    },
    {
      "source": "n109",
      "target": "n32"
    },
    {
      "source": "n110",
      "target": "n56"
    },
    {
      "source": "n120",
      "target": "n98"
    },
    {
      "source": "n50",
      "target": "n109"
    },
    {
      "source": "n110",
      "target": "n40"
    },
    {
      "source": "n9",
      "target": "n110"
    },
    {
      "source": "n114",
      "target": "n41"
    },
    {
      "source": "n61",
      "target": "n119"
    },
    {
      "source": "n71",
      "target": "n111"
    },
    {
      "source": "n113",
      "target": "n20"
    },
    {
      "source": "n120",
      "target": "n6"
    },
    {
      "source": "n76",
      "target": "n113"
    },
    {
      "source": "n32",
      "target": "n114"
    },
    {
      "source": "n25",
      "target": "n110"
    },
    {
      "source": "n112",
      "target": "n79"
    },
    {
      "source": "n119",
      "target": "n41"
    },
    {
      "source": "n119",
      "target": "n61"
    },
    {
      "source": "n118",
      "target": "n2"
    },
    {
      "source": "n43",
      "target": "n109"
    },
    {
      "source": "n8",
      "target": "n114"
    },
    {
      "source": "n60",
      "target": "n117"
    },
    {
      "source": "n117",
      "target": "n66"
    },
    {
      "source": "n119",
      "target": "n46"
    },
    {
      "source": "n71",
      "target": "n112"
    },
    {
      "source": "n47",
      "target": "n114"
    },
    {
      "source": "n34",
      "target": "n109"
    },
    {
      "source": "n112",
      "target": "n22"
    },
    {
      "source": "n26",
      "target": "n117"
    },
    {
      "source": "n120",
      "target": "n28"
    },
    {
      "source": "n109",
      "target": "n40"
    },
    {
      "source": "n116",
      "target": "n102"
    },
    {
      "source": "n117",
      "target": "n63"
    },
    {
      "source": "n70",
      "target": "n117"
    },
    {
      "source": "n34",
      "target": "n114"
    },
    {
      "source": "n36",
      "target": "n116"
    },
    {
      "source": "n109",
      "target": "n2"
    },
    {
      "source": "n54",
      "target": "n113"
    },
    {
      "source": "n72",
      "target": "n114"
    },
    {
      "source": "n115",
      "target": "n76"
    },
    {
      "source": "n114",
      "target": "n69"
    },
    {
      "source": "n78",
      "target": "n117"
    },
    {
      "source": "n50",
      "target": "n112"
    },
    {
      "source": "n117",
      "target": "n78"
    },
    {
      "source": "n113",
      "target": "n65"
    },
    {
      "source": "n116",
      "target": "n35"
    },
    {
      "source": "n50",
      "target": "n114"
    },
    {
      "source": "n92",
      "target": "n115"
    },
    {
      "source": "n114",
      "target": "n29"
    },
    {
      "source": "n16",
      "target": "n114"
    },
    {
      "source": "n114",
      "target": "n51"
    },
    {
      "source": "n91",
      "target": "n116"
    },
    {
      "source": "n63",
      "target": "n120"
    },
    {
      "source": "n110",
      "target": "n98"
    },
    {
      "source": "n111",
      "target": "n30"
    },
    {
      "source": "n116",
      "target": "n25"
    },
    {
      "source": "n120",
      "target": "n72"
    },
    {
      "source": "n117",
      "target": "n73"
    },
    {
      "source": "n37",
      "target": "n113"
    },
    {
      "source": "n113",
      "target": "n64"
    },
    {
      "source": "n110",
      "target": "n94"
    },
    {
      "source": "n108",
      "target": "n81"
    },
    {
      "source": "n116",
      "target": "n27"
    },
    {
      "source": "n113",
      "target": "n71"
    },
    {
      "source": "n114",
      "target": "n7"
    },
    {
      "source": "n69",
      "target": "n120"
    },
    {
      "source": "n110",
      "target": "n76"
    },
    {
      "source": "n64",
      "target": "n116"
    },
    {
      "source": "n34",
      "target": "n110"
    },
    {
      "source": "n118",
      "target": "n89"
    },
    {
      "source": "n114",
      "target": "n14"
    },
    {
      "source": "n103",
      "target": "n111"
    },
    {
      "source": "n4",
      "target": "n114"
    },
    {
      "source": "n113",
      "target": "n79"
    },
    {
      "source": "n109",
      "target": "n101"
    },
    {
      "source": "n65",
      "target": "n119"
    },
    {
      "source": "n113",
      "target": "n77"
    },
    {
      "source": "n30",
      "target": "n110"
    },
    {
      "source": "n119",
      "target": "n32"
    },
    {
      "source": "n120",
      "target": "n40"
    },
    {
      "source": "n42",
      "target": "n117"
    },
    {
      "source": "n110",
      "target": "n10"
    },
    {
      "source": "n113",
      "target": "n36"
    },
    {
      "source": "n105",
      "target": "n113"
    },
    {
      "source": "n112",
      "target": "n80"
    },
    {
      "source": "n118",
      "target": "n79"
    },
    {
      "source": "n71",
      "target": "n116"
    },
    {
      "source": "n115",
      "target": "n53"
    },
    {
      "source": "n109",
      "target": "n19"
    },
    {
      "source": "n21",
      "target": "n113"
    },
    {
      "source": "n67",
      "target": "n119"
    },
    {
      "source": "n112",
      "target": "n40"
    },
    {
      "source": "n108",
      "target": "n29"
    },
    {
      "source": "n112",
      "target": "n61"
    },
    {
      "source": "n34",
      "target": "n113"
    },
    {
      "source": "n79",
      "target": "n109"
    },
    {
      "source": "n36",
      "target": "n113"
    },
    {
      "source": "n110",
      "target": "n31"
    },
    {
      "source": "n14",
      "target": "n108"
    },
    {
      "source": "n113",
      "target": "n72"
    },
    {
      "source": "n112",
      "target": "n43"
    },
    {
      "source": "n38",
      "target": "n120"
    },
    {
      "source": "n110",
      "target": "n43"
    },
    {
      "source": "n113",
      "target": "n96"
    },
    {
      "source": "n45",
      "target": "n111"
    },
    {
      "source": "n72",
      "target": "n108"
    },
    {
      "source": "n79",
      "target": "n113"
    },
    {
      "source": "n16",
      "target": "n120"
    },
    {
      "source": "n71",
      "target": "n114"
    },
    {
      "source": "n20",
      "target": "n111"
    },
    {
      "source": "n58",
      "target": "n117"
    },
    {
      "source": "n114",
      "target": "n67"
    },
    {
      "source": "n119",
      "target": "n35"
    },
    {
      "source": "n117",
      "target": "n99"
    },
    {
      "source": "n8",
      "target": "n111"
    },
    {
      "source": "n82",
      "target": "n119"
    },
    {
      "source": "n3",
      "target": "n113"
    },
    {
      "source": "n116",
      "target": "n103"
    },
    {
      "source": "n119",
      "target": "n48"
    },
    {
      "source": "n97",
      "target": "n117"
    },
    {
      "source": "n61",
      "target": "n109"
    },
    {
      "source": "n5",
      "target": "n115"
    },
    {
      "source": "n7",
      "target": "n113"
    },
    {
      "source": "n109",
      "target": "n4"
    },
    {
      "source": "n120",
      "target": "n74"
    },
    {
      "source": "n96",
      "target": "n113"
    },
    {
      "source": "n43",
      "target": "n111"
    },
    {
      "source": "n100",
      "target": "n120"
    },
    {
      "source": "n118",
      "target": "n77"
    },
    {
      "source": "n119",
      "target": "n12"
    },
    {
      "source": "n68",
      "target": "n116"
    },
    {
      "source": "n112",
      "target": "n4"
    },
    {
      "source": "n50",
      "target": "n116"
    },
    {
      "source": "n22",
      "target": "n113"
    },
    {
      "source": "n117",
      "target": "n90"
    },
    {
      "source": "n120",
      "target": "n3"
    },
    {
      "source": "n108",
      "target": "n73"
    },
    {
      "source": "n65",
      "target": "n111"
    },
    {
      "source": "n108",
      "target": "n45"
    },
    {
      "source": "n2",
      "target": "n113"
    },
    {
      "source": "n109",
      "target": "n50"
    },
    {
      "source": "n113",
      "target": "n13"
    },
    {
      "source": "n120",
      "target": "n71"
    },
    {
      "source": "n32",
      "target": "n116"
    },
    {
      "source": "n116",
      "target": "n18"
    },
    {
      "source": "n94",
      "target": "n109"
    },
    {
      "source": "n114",
      "target": "n105"
    },
    {
      "source": "n116",
      "target": "n106"
    },
    {
      "source": "n113",
      "target": "n91"
    },
    {
      "source": "n24",
      "target": "n113"
    },
    {
      "source": "n113",
      "target": "n75"
    },
    {
      "source": "n35",
      "target": "n119"
    },
    {
      "source": "n21",
      "target": "n109"
    },
    {
      "source": "n24",
      "target": "n110"
    },
    {
      "source": "n74",
      "target": "n110"
    },
    {
      "source": "n115",
      "target": "n70"
    },
    {
      "source": "n111",
      "target": "n90"
    },
    {
      "source": "n113",
      "target": "n100"
    },
    {
      "source": "n120",
      "target": "n79"
    },
    {
      "source": "n63",
      "target": "n114"
    },
    {
      "source": "n105",
      "target": "n109"
    },
    {
      "source": "n108",
      "target": "n55"
    },
    {
      "source": "n110",
      "target": "n4"
    },
    {
      "source": "n75",
      "target": "n119"
    },
    {
      "source": "n118",
      "target": "n60"
    },
    {
      "source": "n118",
      "target": "n5"
    },
    {
      "source": "n107",
      "target": "n118"
    },
    {
      "source": "n112",
      "target": "n31"
    },
    {
      "source": "n113",
      "target": "n68"
    },
    {
      "source": "n111",
      "target": "n56"
    },
    {
      "source": "n118",
      "target": "n75"
    },
    {
      "source": "n33",
      "target": "n108"
    },
    {
      "source": "n36",
      "target": "n114"
    },
    {
      "source": "n115",
      "target": "n101"
    },
    {
      "source": "n11",
      "target": "n113"
    },
    {
      "source": "n113",
      "target": "n83"
    },
    {
      "source": "n17",
      "target": "n115"
    },
    {
      "source": "n92",
      "target": "n114"
    },
    {
      "source": "n8",
      "target": "n113"
    },
    {
      "source": "n113",
      "target": "n67"
    },
    {
      "source": "n111",
      "target": "n25"
    },
    {
      "source": "n66",
      "target": "n120"
    },
    {
      "source": "n6",
      "target": "n114"
    },
    {
      "source": "n109",
      "target": "n16"
    },
    {
      "source": "n110",
      "target": "n11"
    },
    {
      "source": "n5",
      "target": "n109"
    },
    {
      "source": "n101",
      "target": "n113"
    },
    {
      "source": "n120",
      "target": "n96"
    },
    {
      "source": "n116",
      "target": "n6"
    },
    {
      "source": "n12",
      "target": "n119"
    },
    {
      "source": "n32",
      "target": "n119"
    },
    {
      "source": "n116",
      "target": "n40"
    },
    {
      "source": "n118",
      "target": "n23"
    },
    {
      "source": "n114",
      "target": "n33"
    },
    {
      "source": "n119",
      "target": "n98"
    },
    {
      "source": "n57",
      "target": "n116"
    },
    {
      "source": "n82",
      "target": "n116"
    },
    {
      "source": "n120",
      "target": "n59"
    },
    {
      "source": "n83",
      "target": "n114"
    },
    {
      "source": "n117",
      "target": "n21"
    },
    {
      "source": "n113",
      "target": "n87"
    },
    {
      "source": "n4",
      "target": "n109"
    },
    {
      "source": "n119",
      "target": "n39"
    },
    {
      "source": "n116",
      "target": "n80"
    },
    {
      "source": "n24",
      "target": "n114"
    },
    {
      "source": "n29",
      "target": "n108"
    },
    {
      "source": "n115",
      "target": "n78"
    },
    {
      "source": "n113",
      "target": "n35"
    },
    {
      "source": "n110",
      "target": "n71"
    },
    {
      "source": "n110",
      "target": "n96"
    },
    {
      "source": "n69",
      "target": "n108"
    },
    {
      "source": "n98",
      "target": "n116"
    },
    {
      "source": "n109",
      "target": "n3"
    },
    {
      "source": "n117",
      "target": "n50"
    },
    {
      "source": "n110",
      "target": "n50"
    },
    {
      "source": "n112",
      "target": "n5"
    },
    {
      "source": "n120",
      "target": "n4"
    },
    {
      "source": "n98",
      "target": "n119"
    },
    {
      "source": "n115",
      "target": "n84"
    },
    {
      "source": "n34",
      "target": "n112"
    },
    {
      "source": "n72",
      "target": "n113"
    },
    {
      "source": "n71",
      "target": "n109"
    },
    {
      "source": "n112",
      "target": "n94"
    },
    {
      "source": "n99",
      "target": "n120"
    },
    {
      "source": "n110",
      "target": "n79"
    },
    {
      "source": "n111",
      "target": "n46"
    },
    {
      "source": "n117",
      "target": "n52"
    },
    {
      "source": "n79",
      "target": "n116"
    },
    {
      "source": "n111",
      "target": "n24"
    },
    {
      "source": "n47",
      "target": "n113"
    },
    {
      "source": "n33",
      "target": "n114"
    },
    {
      "source": "n39",
      "target": "n111"
    },
    {
      "source": "n23",
      "target": "n115"
    },
    {
      "source": "n112",
      "target": "n76"
    },
    {
      "source": "n95",
      "target": "n111"
    },
    {
      "source": "n112",
      "target": "n54"
    },
    {
      "source": "n100",
      "target": "n116"
    },
    {
      "source": "n64",
      "target": "n117"
    },
    {
      "source": "n113",
      "target": "n44"
    },
    {
      "source": "n118",
      "target": "n58"
    },
    {
      "source": "n120",
      "target": "n88"
    },
    {
      "source": "n115",
      "target": "n4"
    },
    {
      "source": "n111",
      "target": "n55"
    },
    {
      "source": "n28",
      "target": "n111"
    },
    {
      "source": "n72",
      "target": "n116"
    },
    {
      "source": "n112",
      "target": "n96"
    },
    {
      "source": "n118",
      "target": "n27"
    },
    {
      "source": "n109",
      "target": "n8"
    },
    {
      "source": "n115",
      "target": "n58"
    },
    {
      "source": "n19",
      "target": "n108"
    },
    {
      "source": "n11",
      "target": "n111"
    },
    {
      "source": "n120",
      "target": "n83"
    },
    {
      "source": "n91",
      "target": "n119"
    },
    {
      "source": "n89",
      "target": "n115"
    },
    {
      "source": "n17",
      "target": "n108"
    },
    {
      "source": "n115",
      "target": "n26"
    },
    {
      "source": "n110",
      "target": "n104"
    },
    {
      "source": "n29",
      "target": "n111"
    },
    {
      "source": "n109",
      "target": "n34"
    },
    {
      "source": "n112",
      "target": "n44"
    },
    {
      "source": "n119",
      "target": "n10"
    },
    {
      "source": "n50",
      "target": "n120"
    },
    {
      "source": "n112",
      "target": "n50"
    },
    {
      "source": "n114",
      "target": "n49"
    },
    {
      "source": "n96",
      "target": "n112"
    },
    {
      "source": "n44",
      "target": "n116"
    },
    {
      "source": "n113",
      "target": "n32"
    },
    {
      "source": "n44",
      "target": "n113"
    },
    {
      "source": "n117",
      "target": "n38"
    },
    {
      "source": "n22",
      "target": "n114"
    },
    {
      "source": "n31",
      "target": "n110"
    },
    {
      "source": "n98",
      "target": "n112"
    },
    {
      "source": "n113",
      "target": "n40"
    },
    {
      "source": "n115",
      "target": "n97"
    },
    {
      "source": "n74",
      "target": "n114"
    },
    {
      "source": "n116",
      "target": "n104"
    },
    {
      "source": "n1",
      "target": "n110"
    },
    {
      "source": "n113",
      "target": "n70"
    },
    {
      "source": "n4",
      "target": "n113"
    },
    {
      "source": "n3",
      "target": "n114"
    },
    {
      "source": "n12",
      "target": "n116"
    },
    {
      "source": "n3",
      "target": "n109"
    },
    {
      "source": "n66",
      "target": "n115"
    },
    {
      "source": "n73",
      "target": "n120"
    },
    {
      "source": "n52",
      "target": "n120"
    },
    {
      "source": "n110",
      "target": "n44"
    },
    {
      "source": "n41",
      "target": "n108"
    },
    {
      "source": "n119",
      "target": "n82"
    },
    {
      "source": "n16",
      "target": "n113"
    },
    {
      "source": "n113",
      "target": "n99"
    },
    {
      "source": "n48",
      "target": "n115"
    },
    {
      "source": "n90",
      "target": "n120"
    },
    {
      "source": "n117",
      "target": "n100"
    },
    {
      "source": "n79",
      "target": "n112"
    },
    {
      "source": "n77",
      "target": "n115"
    },
    {
      "source": "n109",
      "target": "n71"
    },
    {
      "source": "n111",
      "target": "n31"
    },
    {
      "source": "n15",
      "target": "n117"
    },
    {
      "source": "n109",
      "target": "n36"
    },
    {
      "source": "n19",
      "target": "n113"
    },
    {
      "source": "n110",
      "target": "n34"
    },
    {
      "source": "n84",
      "target": "n117"
    },
    {
      "source": "n93",
      "target": "n108"
    },
    {
      "source": "n49",
      "target": "n108"
    },
    {
      "source": "n40",
      "target": "n116"
    },
    {
      "source": "n119",
      "target": "n88"
    },
    {
      "source": "n101",
      "target": "n114"
    },
    {
      "source": "n110",
      "target": "n3"
    },
    {
      "source": "n72",
      "target": "n112"
    },
    {
      "source": "n45",
      "target": "n117"
    },
    {
      "source": "n108",
      "target": "n8"
    },
    {
      "source": "n111",
      "target": "n84"
    },
    {
      "source": "n27",
      "target": "n115"
    },
    {
      "source": "n62",
      "target": "n120"
    },
    {
      "source": "n120",
      "target": "n92"
    },
    {
      "source": "n108",
      "target": "n11"
    },
    {
      "source": "n14",
      "target": "n110"
    },
    {
      "source": "n109",
      "target": "n79"
    },
    {
      "source": "n113",
      "target": "n102"
    },
    {
      "source": "n120",
      "target": "n33"
    },
    {
      "source": "n110",
      "target": "n54"
    },
    {
      "source": "n119",
      "target": "n65"
    },
    {
      "source": "n96",
      "target": "n116"
    },
    {
      "source": "n114",
      "target": "n57"
    },
    {
      "source": "n119",
      "target": "n64"
    },
    {
      "source": "n86",
      "target": "n108"
    },
    {
      "source": "n75",
      "target": "n115"
    },
    {
      "source": "n32",
      "target": "n113"
    },
    {
      "source": "n56",
      "target": "n113"
    },
    {
      "source": "n30",
      "target": "n115"
    },
    {
      "source": "n31",
      "target": "n113"
    },
    {
      "source": "n18",
      "target": "n108"
    },
    {
      "source": "n108",
      "target": "n43"
    },
    {
      "source": "n116",
      "target": "n52"
    },
    {
      "source": "n112",
      "target": "n105"
    },
    {
      "source": "n110",
      "target": "n23"
    },
    {
      "source": "n4",
      "target": "n116"
    },
    {
      "source": "n68",
      "target": "n113"
    },
    {
      "source": "n112",
      "target": "n71"
    },
    {
      "source": "n118",
      "target": "n92"
    },
    {
      "source": "n1",
      "target": "n116"
    },
    {
      "source": "n67",
      "target": "n116"
    },
    {
      "source": "n115",
      "target": "n15"
    },
    {
      "source": "n56",
      "target": "n110"
    },
    {
      "source": "n59",
      "target": "n114"
    },
    {
      "source": "n110",
      "target": "n87"
    },
    {
      "source": "n118",
      "target": "n17"
    },
    {
      "source": "n111",
      "target": "n74"
    },
    {
      "source": "n120",
      "target": "n97"
    },
    {
      "source": "n110",
      "target": "n15"
    },
    {
      "source": "n78",
      "target": "n120"
    },
    {
      "source": "n58",
      "target": "n115"
    },
    {
      "source": "n111",
      "target": "n91"
    },
    {
      "source": "n82",
      "target": "n114"
    },
    {
      "source": "n79",
      "target": "n115"
    },
    {
      "source": "n79",
      "target": "n114"
    },
    {
      "source": "n104",
      "target": "n113"
    },
    {
      "source": "n76",
      "target": "n117"
    },
    {
      "source": "n115",
      "target": "n42"
    },
    {
      "source": "n65",
      "target": "n116"
    },
    {
      "source": "n113",
      "target": "n50"
    },
    {
      "source": "n5",
      "target": "n113"
    },
    {
      "source": "n21",
      "target": "n120"
    },
    {
      "source": "n117",
      "target": "n62"
    },
    {
      "source": "n119",
      "target": "n42"
    },
    {
      "source": "n118",
      "target": "n48"
    },
    {
      "source": "n20",
      "target": "n116"
    },
    {
      "source": "n112",
      "target": "n21"
    },
    {
      "source": "n113",
      "target": "n4"
    },
    {
      "source": "n2",
      "target": "n115"
    },
    {
      "source": "n40",
      "target": "n112"
    },
    {
      "source": "n68",
      "target": "n119"
    },
    {
      "source": "n110",
      "target": "n21"
    },
    {
      "source": "n44",
      "target": "n109"
    },
    {
      "source": "n96",
      "target": "n114"
    },
    {
      "source": "n110",
      "target": "n72"
    },
    {
      "source": "n7",
      "target": "n108"
    },
    {
      "source": "n31",
      "target": "n109"
    },
    {
      "source": "n110",
      "target": "n85"
    },
    {
      "source": "n108",
      "target": "n103"
    },
    {
      "source": "n113",
      "target": "n12"
    },
    {
      "source": "n4",
      "target": "n112"
    },
    {
      "source": "n119",
      "target": "n68"
    },
    {
      "source": "n113",
      "target": "n1"
    },
    {
      "source": "n110",
      "target": "n68"
    },
    {
      "source": "n110",
      "target": "n5"
    },
    {
      "source": "n75",
      "target": "n116"
    },
    {
      "source": "n71",
      "target": "n113"
    },
    {
      "source": "n119",
      "target": "n91"
    },
    {
      "source": "n113",
      "target": "n57"
    },
    {
      "source": "n98",
      "target": "n113"
    },
    {
      "source": "n90",
      "target": "n110"
    },
    {
      "source": "n37",
      "target": "n120"
    },
    {
      "source": "n119",
      "target": "n75"
    },
    {
      "source": "n117",
      "target": "n69"
    },
    {
      "source": "n109",
      "target": "n96"
    },
    {
      "source": "n13",
      "target": "n116"
    },
    {
      "source": "n34",
      "target": "n116"
    },
    {
      "source": "n35",
      "target": "n116"
    },
    {
      "source": "n119",
      "target": "n38"
    },
    {
      "source": "n64",
      "target": "n119"
    },
    {
      "source": "n114",
      "target": "n93"
    },
    {
      "source": "n110",
      "target": "n105"
    },
    {
      "source": "n120",
      "target": "n50"
    },
    {
      "source": "n70",
      "target": "n116"
    },
    {
      "source": "n88",
      "target": "n114"
    },
    {
      "source": "n112",
      "target": "n72"
    },
    {
      "source": "n114",
      "target": "n18"
    },
    {
      "source": "n57",
      "target": "n108"
    },
    {
      "source": "n111",
      "target": "n14"
    },
    {
      "source": "n84",
      "target": "n110"
    },
    {
      "source": "n15",
      "target": "n113"
    },
    {
      "source": "n80",
      "target": "n109"
    },
    {
      "source": "n119",
      "target": "n67"
    },
    {
      "source": "n85",
      "target": "n113"
    }
  ]
}